design_patterns/__init__.py
design_patterns_WS-1.0.0.dist-info/LICENSE
design_patterns_WS-1.0.0.dist-info/METADATA
design_patterns_WS-1.0.0.dist-info/WHEEL
design_patterns_WS-1.0.0.dist-info/top_level.txt
design_patterns_WS-1.0.0.dist-info/RECORD
