Metadata-Version: 2.1
Name: design-patterns-WS
Version: 1.0.0
Summary: A small python module containing decorators for implementing design patterns
Home-page: https://github.com/wassafshahzad/DesignPatterns.git
Author: Wassaf Shahzad
Author-email: wassafshahzad@gmail.com
License: UNKNOWN
Platform: UNKNOWN
Classifier: Programming Language :: Python :: 3
Classifier: License :: OSI Approved :: MIT License
Classifier: Operating System :: OS Independent
Requires-Python: >=3.3
